{
    "$schema": "https://bot.prismboat.com/",
    "theme": "willow",
    "name": "PrismBoat",
    "colors": {
        "primary": "#396cc9",
        "light": "#ffffff",
        "dark": "#000000"
    },
    "favicon": "images/3.png",
    "navigation": {
        "tabs": [
            {
                "tab": "Quick Start",
                "groups": [
                    {
                        "group": "Quick Start",
                        "pages": [
                            "docs",
                            "quickstart",
                            "development"
                        ]
                    },
                    {
                        "group": "Commands",
                        "pages": [
                            "/commands/overview",
                            "/commands/images",
                            "/commands/settings",
                            "/commands/navigation",
                            "/commands/reusable-snippets"
                        ]
                    }
                ]
            }
        ],
        "global": {
            "anchors": [
                {
                    "anchor": "Dashboard",
                    "href": "https://bot.prismboat.com/",
                    "icon": "grid-horizontal"
                },
                {
                    "anchor": "Support",
                    "href": "https://discord.prismboat.com/",
                    "icon": "discord"
                }
            ]
        }
    },
    "logo": {
        "light": "/images/3.png",
        "dark": "/images/3.png"
    },
    "navbar": {
        "links": [
            {
                "label": "Support",
                "href": "https://discord.prismboat.com/"
            }
        ],
        "primary": {
            "type": "button",
            "label": "Dashboard",
            "href": "https://bot.prismboat.com/"
        }
    },
    "footer": {
        "socials": {
            "discord": "https://discord.prismboat.com/"
        }
    }
}